huaweicloudsdkcse/__init__.py
huaweicloudsdkcse/v1/__init__.py
huaweicloudsdkcse/v1/cse_async_client.py
huaweicloudsdkcse/v1/cse_client.py
huaweicloudsdkcse/v1/model/__init__.py
huaweicloudsdkcse/v1/model/cluster_node.py
huaweicloudsdkcse/v1/model/create_bussiness_scene.py
huaweicloudsdkcse/v1/model/create_bussiness_scene_spec.py
huaweicloudsdkcse/v1/model/create_bussiness_scene_spec_matches.py
huaweicloudsdkcse/v1/model/create_engine_request.py
huaweicloudsdkcse/v1/model/create_engine_response.py
huaweicloudsdkcse/v1/model/create_gov_policy.py
huaweicloudsdkcse/v1/model/create_governance_policy_request.py
huaweicloudsdkcse/v1/model/create_governance_policy_response.py
huaweicloudsdkcse/v1/model/create_http2_rpc_request.py
huaweicloudsdkcse/v1/model/create_http2_rpc_response.py
huaweicloudsdkcse/v1/model/create_kie_req.py
huaweicloudsdkcse/v1/model/create_match.py
huaweicloudsdkcse/v1/model/create_match_headers.py
huaweicloudsdkcse/v1/model/create_match_headers_header.py
huaweicloudsdkcse/v1/model/create_microservice_route_rule_request.py
huaweicloudsdkcse/v1/model/create_microservice_route_rule_response.py
huaweicloudsdkcse/v1/model/create_nacos_namespaces_request.py
huaweicloudsdkcse/v1/model/create_nacos_namespaces_response.py
huaweicloudsdkcse/v1/model/create_plugin_request.py
huaweicloudsdkcse/v1/model/create_plugin_response.py
huaweicloudsdkcse/v1/model/create_route.py
huaweicloudsdkcse/v1/model/create_route_tags.py
huaweicloudsdkcse/v1/model/create_rules.py
huaweicloudsdkcse/v1/model/delete_engine_request.py
huaweicloudsdkcse/v1/model/delete_engine_response.py
huaweicloudsdkcse/v1/model/delete_governance_policy_request.py
huaweicloudsdkcse/v1/model/delete_governance_policy_response.py
huaweicloudsdkcse/v1/model/delete_http2_rpc_request.py
huaweicloudsdkcse/v1/model/delete_http2_rpc_response.py
huaweicloudsdkcse/v1/model/delete_microservice_route_rule_request.py
huaweicloudsdkcse/v1/model/delete_microservice_route_rule_response.py
huaweicloudsdkcse-3.1.184.dist-info/METADATA
huaweicloudsdkcse-3.1.184.dist-info/WHEEL
huaweicloudsdkcse-3.1.184.dist-info/licenses/LICENSE
huaweicloudsdkcse-3.1.184.dist-info/RECORD
